nepse_scraper/__init__.py
nepse_scraper/auth.py
nepse_scraper/client.py
nepse_scraper/core.py
nepse_scraper/endpoints.py
nepse_scraper/exceptions.py
nepse_scraper/nepse.wasm
nepse_scraper-1.0.0.dist-info/METADATA
nepse_scraper-1.0.0.dist-info/WHEEL
nepse_scraper-1.0.0.dist-info/licenses/LICENSE.txt
nepse_scraper-1.0.0.dist-info/RECORD
