Metadata-Version: 2.4
Name: nepse-scraper
Version: 1.0.0
Summary: 
License: MIT
License-File: LICENSE.txt
Author: polymorphisma
Author-email: shrawansunar.6@gmail.com
Requires-Python: >=3.10
Classifier: License :: OSI Approved :: MIT License
Classifier: Programming Language :: Python :: 3
Classifier: Programming Language :: Python :: 3.10
Classifier: Programming Language :: Python :: 3.11
Classifier: Programming Language :: Python :: 3.12
Classifier: Programming Language :: Python :: 3.13
Classifier: Programming Language :: Python :: 3.14
Requires-Dist: certifi (>=2021.5.30)
Requires-Dist: requests (>=2.25.1)
Requires-Dist: wasmtime (>=18.0.0)
